odoo9_addon_l10n_es_aeat_mod303-9.0.1.8.0-py2.7-nspkg.pth
odoo9_addon_l10n_es_aeat_mod303-9.0.1.8.0.dist-info/DESCRIPTION.rst
odoo9_addon_l10n_es_aeat_mod303-9.0.1.8.0.dist-info/METADATA
odoo9_addon_l10n_es_aeat_mod303-9.0.1.8.0.dist-info/RECORD
odoo9_addon_l10n_es_aeat_mod303-9.0.1.8.0.dist-info/WHEEL
odoo9_addon_l10n_es_aeat_mod303-9.0.1.8.0.dist-info/metadata.json
odoo9_addon_l10n_es_aeat_mod303-9.0.1.8.0.dist-info/namespace_packages.txt
odoo9_addon_l10n_es_aeat_mod303-9.0.1.8.0.dist-info/top_level.txt
odoo_addons/l10n_es_aeat_mod303/README.rst
odoo_addons/l10n_es_aeat_mod303/__init__.py
odoo_addons/l10n_es_aeat_mod303/__openerp__.py
odoo_addons/l10n_es_aeat_mod303/data/aeat_export_mod303_2017_data.xml
odoo_addons/l10n_es_aeat_mod303/data/aeat_export_mod303_2018_data.xml
odoo_addons/l10n_es_aeat_mod303/data/aeat_export_mod303_data.xml
odoo_addons/l10n_es_aeat_mod303/data/tax_code_map_mod303_data.xml
odoo_addons/l10n_es_aeat_mod303/docs/303_register_design_e15v32.xlsx
odoo_addons/l10n_es_aeat_mod303/docs/DR303e15v34.xlsx
odoo_addons/l10n_es_aeat_mod303/docs/DR303e17v20_04.xlsx
odoo_addons/l10n_es_aeat_mod303/docs/DR303e18v10_00.xlsx
odoo_addons/l10n_es_aeat_mod303/docs/instr_mod303.pdf
odoo_addons/l10n_es_aeat_mod303/i18n/bg.po
odoo_addons/l10n_es_aeat_mod303/i18n/ca.po
odoo_addons/l10n_es_aeat_mod303/i18n/cs.po
odoo_addons/l10n_es_aeat_mod303/i18n/es.po
odoo_addons/l10n_es_aeat_mod303/i18n/es_CO.po
odoo_addons/l10n_es_aeat_mod303/i18n/es_CR.po
odoo_addons/l10n_es_aeat_mod303/i18n/eu.po
odoo_addons/l10n_es_aeat_mod303/i18n/fr.po
odoo_addons/l10n_es_aeat_mod303/i18n/gl.po
odoo_addons/l10n_es_aeat_mod303/i18n/hr.po
odoo_addons/l10n_es_aeat_mod303/i18n/l10n_es_aeat_mod303.pot
odoo_addons/l10n_es_aeat_mod303/i18n/nl.po
odoo_addons/l10n_es_aeat_mod303/i18n/pl.po
odoo_addons/l10n_es_aeat_mod303/i18n/pt.po
odoo_addons/l10n_es_aeat_mod303/i18n/pt_BR.po
odoo_addons/l10n_es_aeat_mod303/i18n/ru.po
odoo_addons/l10n_es_aeat_mod303/i18n/sl.po
odoo_addons/l10n_es_aeat_mod303/i18n/sv.po
odoo_addons/l10n_es_aeat_mod303/i18n/tr.po
odoo_addons/l10n_es_aeat_mod303/i18n/vi.po
odoo_addons/l10n_es_aeat_mod303/models/__init__.py
odoo_addons/l10n_es_aeat_mod303/models/mod303.py
odoo_addons/l10n_es_aeat_mod303/security/ir.model.access.csv
odoo_addons/l10n_es_aeat_mod303/security/l10n_es_aeat_mod303_security.xml
odoo_addons/l10n_es_aeat_mod303/static/description/icon.png
